setup.py
dataplunger/__init__.py
dataplunger/core.py
dataplunger/processors.py
dataplunger/readers.py
dataplunger.egg-info/PKG-INFO
dataplunger.egg-info/SOURCES.txt
dataplunger.egg-info/dependency_links.txt
dataplunger.egg-info/requires.txt
dataplunger.egg-info/top_level.txt