Metadata-Version: 1.1
Name: dataplunger
Version: 0.1.0
Summary: Extract, Transform, Load
Home-page: https://github.com/mattmakesmaps/dataplunger
Author: Matthew Kenny
Author-email: matthewkenny AT gmail DOT com
License: GNU GENERAL PUBLIC LICENSE V2
Keywords: gis etl
Platform: UNKNOWN
Classifier: Development Status :: 4 - Beta
Classifier: Topic :: Scientific/Engineering :: GIS
Classifier: License :: OSI Approved :: GNU General Public License v2 (GPLv2)
Classifier: Intended Audience :: Developers
